divipy.py
divipy-1.0.2.dist-info/METADATA
divipy-1.0.2.dist-info/WHEEL
divipy-1.0.2.dist-info/top_level.txt
divipy-1.0.2.dist-info/RECORD
