Metadata-Version: 2.1
Name: divipy
Version: 1.0.2
Summary: Perfect and Cool package for developers.
Author-email: Pandaxyz <contact@tourble.org>
Project-URL: Homepage, https://github.com/Pandaxyz-xd/divipy
Project-URL: Bug Tracker, https://github.com/Pandaxyz-xd/divipy/issues
Classifier: Programming Language :: Python :: 3
Classifier: License :: OSI Approved :: MIT License
Classifier: Operating System :: OS Independent
Requires-Python: >=3.7
